gwak.py
libgwak/__init__.py
libgwak/manifest.py
libgwak/zy.py
gwak-0.6.1.dist-info/LICENSE
gwak-0.6.1.dist-info/METADATA
gwak-0.6.1.dist-info/WHEEL
gwak-0.6.1.dist-info/entry_points.txt
gwak-0.6.1.dist-info/top_level.txt
gwak-0.6.1.dist-info/RECORD
